AUTHORS
CONTRIBUTING.md
Changelog.rst
LICENSE
MANIFEST.in
README
README.rst
setup.cfg
setup.py
tox.ini
docs/Changelog.rst
docs/Makefile
docs/api.rst
docs/conf.py
docs/connection.rst
docs/exceptions.rst
docs/helpers.rst
docs/index.rst
docs/transports.rst
elasticsearch/__init__.py
elasticsearch/compat.py
elasticsearch/connection_pool.py
elasticsearch/exceptions.py
elasticsearch/serializer.py
elasticsearch/transport.py
elasticsearch/addon/__init__.py
elasticsearch/addon/bdoc.py
elasticsearch/client/__init__.py
elasticsearch/client/cat.py
elasticsearch/client/cluster.py
elasticsearch/client/indices.py
elasticsearch/client/nodes.py
elasticsearch/client/snapshot.py
elasticsearch/client/tasks.py
elasticsearch/client/utils.py
elasticsearch/connection/__init__.py
elasticsearch/connection/base.py
elasticsearch/connection/http_requests.py
elasticsearch/connection/http_urllib3.py
elasticsearch/connection/pooling.py
elasticsearch/helpers/__init__.py
elasticsearch/helpers/test.py
elasticsearch_bdoc.egg-info/PKG-INFO
elasticsearch_bdoc.egg-info/SOURCES.txt
elasticsearch_bdoc.egg-info/dependency_links.txt
elasticsearch_bdoc.egg-info/requires.txt
elasticsearch_bdoc.egg-info/top_level.txt